MANIFEST.in
mdx_subscript.py
mdx_superscript.py
mdx_urlize.py
setup.py
marky/__init__.py
marky/markup.py
marky/models.py
marky/urls.py
marky/views.py
marky.egg-info/PKG-INFO
marky.egg-info/SOURCES.txt
marky.egg-info/dependency_links.txt
marky.egg-info/requires.txt
marky.egg-info/top_level.txt
marky/static/marky/css/markup.css
marky/static/marky/css/normalize.css
marky/static/marky/css/style.css
marky/static/marky/css/pygments/default.css
marky/static/marky/js/jquery.js
marky/static/marky/js/main.js
marky/templates/marky/default.txt
marky/templates/marky/preview.html
marky/templatetags/__init__.py
marky/templatetags/marky_tags.py