Metadata-Version: 1.1
Name: marky
Version: 0.9.8
Summary: Markdown editor and previewer
Home-page: https://github.com/bruth/marky/
Author: Byron Ruth
Author-email: b@devel.io
License: BSD
Keywords: markdown markup preview editor
Platform: UNKNOWN
Classifier: Development Status :: 5 - Production/Stable
Classifier: License :: OSI Approved :: BSD License
Classifier: Topic :: Text Processing :: Markup
